[{
    "image": "portfolio.png",
    "title": "Project 1",
    "text": "Lorem ipsum tren vallning hexade såsom pågåt. Kvasilgen öbel prekanar. Osunat prebeliga bävls.",
    "link": "https://www.figma.com/proto/IsvvrtYEZJNHAAfpJsyBxW/Blok-2-SLB-Workout-app?node-id=105-3&t=hnGenhcS1xf4FUlF-0&scaling=scale-down&content-scaling=fixed&page-id=0%3A1&starting-point-node-id=105%3A3&show-proto-sidebar=1&hide-ui=1"
},
{
    "image": "reizen.png",
    "title": "Project 1",
    "text": "Lorem ipsum tren vallning hexade såsom pågåt. Kvasilgen öbel prekanar. Osunat prebeliga bävls",
    "link": "https://kmd98x.github.io/kmdportfolio/index.html"
},
{
    "image": "workout.png",
    "title": "Project 2",
    "text": "Lorem ipsum tren vallning hexade såsom pågåt. Kvasilgen öbel prekanar. Osunat prebeliga bävls."
},
{
    "image": "bib.png",
    "title": "Project 1",
    "text": "Lorem ipsum tren vallning hexade såsom pågåt. Kvasilgen öbel prekanar. Osunat prebeliga bävls"
},
{
    "image": "parfum.png",
    "title": "Project 1",
    "text": "Lorem ipsum tren vallning hexade såsom pågåt. Kvasilgen öbel prekanar. Osunat prebeliga bävls"
},
{
    "image": "duurzaam.png",
    "title": "Project 1",
    "text": "Lorem ipsum tren vallning hexade såsom pågåt. Kvasilgen öbel prekanar. Osunat prebeliga bävls"
},
{
    "image": "kmd.png",
    "title": "Project 1",
    "text": "Lorem ipsum tren vallning hexade såsom pågåt. Kvasilgen öbel prekanar. Osunat prebeliga bävls",
    "link": "https://www.figma.com/proto/IsvvrtYEZJNHAAfpJsyBxW/Blok-2-SLB-Workout-app?node-id=105-3&t=hnGenhcS1xf4FUlF-0&scaling=scale-down&content-scaling=fixed&page-id=0%3A1&starting-point-node-id=105%3A3&show-proto-sidebar=1&hide-ui=1"
},
{
    "image": "flyers.png",
    "title": "Project 1",
    "text": "Lorem ipsum tren vallning hexade såsom pågåt. Kvasilgen öbel prekanar. Osunat prebeliga bävls"
},
{
    "image": "hema.png",
    "title": "Project 1",
    "text": "Lorem ipsum tren vallning hexade såsom pågåt. Kvasilgen öbel prekanar. Osunat prebeliga bävls"
}
]